dionysus/__init__.py
dionysus/_dionysus.cpython-311-x86_64-linux-gnu.so
dionysus/plot.py
dionysus/zigzag.py
dionysus-2.1.8.dist-info/METADATA
dionysus-2.1.8.dist-info/WHEEL
dionysus-2.1.8.dist-info/RECORD
dionysus-2.1.8.dist-info/licenses/LICENSE.txt
dionysus-2.1.8.dist-info/licenses/NOTICES.txt
