Metadata-Version: 2.4
Name: dionysus
Version: 2.1.8
Summary: Library for computing persistent homology
Author-Email: Dmitriy Morozov <dmitriy@mrzv.org>
License-Expression: BSD-3-Clause-LBNL
Classifier: Development Status :: 5 - Production/Stable
Classifier: Intended Audience :: Developers
Classifier: Intended Audience :: Education
Classifier: Intended Audience :: Science/Research
Classifier: Topic :: Software Development :: Libraries :: Python Modules
Classifier: Topic :: Utilities
Classifier: Programming Language :: C++
Classifier: Programming Language :: Python :: 3.12
Project-URL: Homepage, https://github.com/mrzv/dionysus
Project-URL: Documentation, https://www.mrzv.org/software/dionysus2
Project-URL: Repository, https://github.com/mrzv/dionysus.git
Project-URL: Issues, https://github.com/mrzv/dionysus/issues
Requires-Python: >=3.9
Requires-Dist: intervaltree>=3.1.0
Requires-Dist: numpy>=2
